fluxibly/__init__.py
fluxibly/cli.py
fluxibly/agent/__init__.py
fluxibly/agent/base.py
fluxibly/agent/config.py
fluxibly/agent/conversation.py
fluxibly/config/__init__.py
fluxibly/config/loader.py
fluxibly/llm/__init__.py
fluxibly/llm/base.py
fluxibly/llm/custom_llm.py
fluxibly/llm/langchain_llm.py
fluxibly/llm/litellm_llm.py
fluxibly/mcp_client/README.md
fluxibly/mcp_client/__init__.py
fluxibly/mcp_client/manager.py
fluxibly/orchestrator/__init__.py
fluxibly/orchestrator/agent.py
fluxibly/orchestrator/executor.py
fluxibly/orchestrator/planner.py
fluxibly/orchestrator/selector.py
fluxibly/orchestrator/synthesizer.py
fluxibly/orchestrator/config/__init__.py
fluxibly/orchestrator/config/prompts.py
fluxibly/schema/__init__.py
fluxibly/schema/input.py
fluxibly/state/__init__.py
fluxibly/state/config.py
fluxibly/state/manager.py
fluxibly/state/models.py
fluxibly/state/repository.py
fluxibly/state/schema.py
fluxibly/tools/__init__.py
fluxibly/tools/aggregator.py
fluxibly/workflow/__init__.py
fluxibly/workflow/config.py
fluxibly/workflow/engine.py
fluxibly-0.1.0.dist-info/METADATA
fluxibly-0.1.0.dist-info/WHEEL
fluxibly-0.1.0.dist-info/entry_points.txt
fluxibly-0.1.0.dist-info/licenses/LICENSE
fluxibly-0.1.0.dist-info/RECORD
