Metadata-Version: 2.4
Name: fluxibly
Version: 0.1.0
Summary: MCP-Native Agentic Framework for General-Purpose Task Automation
Project-URL: Homepage, https://github.com/Lavaflux/fluxibly
Project-URL: Documentation, https://github.com/Lavaflux/fluxibly#readme
Project-URL: Repository, https://github.com/Lavaflux/fluxibly
Project-URL: Issues, https://github.com/Lavaflux/fluxibly/issues
Author-email: Lavaflux <209tungns@gmail.com>
License: MIT
License-File: LICENSE
Keywords: agent,ai,automation,langchain,langgraph,mcp,workflow
Classifier: Development Status :: 3 - Alpha
Classifier: Intended Audience :: Developers
Classifier: License :: OSI Approved :: MIT License
Classifier: Programming Language :: Python :: 3
Classifier: Programming Language :: Python :: 3.11
Classifier: Programming Language :: Python :: 3.12
Classifier: Topic :: Scientific/Engineering :: Artificial Intelligence
Classifier: Topic :: Software Development :: Libraries :: Python Modules
Requires-Python: >=3.11
Requires-Dist: anyio>=4.0.0
Requires-Dist: httpx>=0.27.0
Requires-Dist: langchain-anthropic>=1.2.0
Requires-Dist: langchain-core>=0.3.0
Requires-Dist: langchain-openai>=0.2.0
Requires-Dist: langchain>=0.3.0
Requires-Dist: langgraph>=0.2.0
Requires-Dist: litellm>=1.80.9
Requires-Dist: loguru>=0.7.3
Requires-Dist: mcp>=1.0.0
Requires-Dist: pydantic-settings>=2.0.0
Requires-Dist: pydantic>=2.0.0
Requires-Dist: python-dotenv>=1.0.0
Requires-Dist: pyyaml>=6.0
Requires-Dist: qdrant-client>=1.16.2
Requires-Dist: rich>=13.0.0
Requires-Dist: sentence-transformers>=5.2.0
Requires-Dist: structlog>=24.0.0
Provides-Extra: dev
Requires-Dist: mkdocs-material>=9.5.0; extra == 'dev'
Requires-Dist: mkdocs>=1.5.0; extra == 'dev'
Requires-Dist: pyright>=1.1.0; extra == 'dev'
Requires-Dist: pytest-asyncio>=0.23.0; extra == 'dev'
Requires-Dist: pytest-cov>=4.1.0; extra == 'dev'
Requires-Dist: pytest-mock>=3.12.0; extra == 'dev'
Requires-Dist: pytest>=8.0.0; extra == 'dev'
Requires-Dist: ruff>=0.8.0; extra == 'dev'
Provides-Extra: mcp-servers
Requires-Dist: opencv-python>=4.9.0; extra == 'mcp-servers'
Requires-Dist: openpyxl>=3.1.0; extra == 'mcp-servers'
Requires-Dist: pandas>=2.2.0; extra == 'mcp-servers'
Requires-Dist: pdf2image>=1.17.0; extra == 'mcp-servers'
Requires-Dist: pillow>=10.0.0; extra == 'mcp-servers'
Requires-Dist: pytesseract>=0.3.10; extra == 'mcp-servers'
